{
  "version": 3,
  "middleware": {
    "/": {
      "files": [
        "server/edge-runtime-webpack.js",
        "server/middleware.js"
      ],
      "name": "middleware",
      "page": "/",
      "matchers": [
        {
          "missing": [
            {
              "type": "header",
              "key": "next-router-prefetch"
            },
            {
              "type": "header",
              "key": "purpose",
              "value": "prefetch"
            }
          ],
          "regexp": "^(?:\\/(_next\\/data\\/[^/]{1,}))?(?:\\/((?!api|_next\\/static|_next\\/image|favicon.ico|icon.ico).*))(\\.json)?[\\/#\\?]?$",
          "originalSource": "/((?!api|_next/static|_next/image|favicon.ico|icon.ico).*)"
        }
      ],
      "wasm": [],
      "assets": [],
      "env": {
        "__NEXT_BUILD_ID": "j3mGHAT3qRkytYx5wk5bA",
        "NEXT_SERVER_ACTIONS_ENCRYPTION_KEY": "vl7lX+GWeCbPFhgdwNZZ0TPJGzPUz+tIp+m02JTUJfY=",
        "__NEXT_PREVIEW_MODE_ID": "1592e9d9e03988f889a018822600b3b9",
        "__NEXT_PREVIEW_MODE_ENCRYPTION_KEY": "043bbd35009120d8239db67cfa89d41f57f2589bb14fdcb8ba31286537faed79",
        "__NEXT_PREVIEW_MODE_SIGNING_KEY": "77f8aabcfd0498037c616e09108fe1264ca1704ad521beae8c13aa49cb8fc38e"
      }
    }
  },
  "functions": {},
  "sortedMiddleware": [
    "/"
  ]
}